LICENSE
README.rst
pyproject.toml
openet/.DS_Store
openet/__init__.py
openet/core/.DS_Store
openet/core/__init__.py
openet/core/common.py
openet/core/ensemble.py
openet/core/export.py
openet/core/interpolate.py
openet/core/landsat.py
openet/core/utils.py
openet/core/wrs2.py
openet/core/tests/conftest.py
openet/core/tests/test_a_utils.py
openet/core/tests/test_b_landsat.py
openet/core/tests/test_common.py
openet/core/tests/test_ensemble.py
openet/core/tests/test_export.py
openet/core/tests/test_interpolate.py
openet/core/tests/test_interpolate2.py
openet/core/tests/.pytest_cache/.gitignore
openet/core/tests/.pytest_cache/CACHEDIR.TAG
openet/core/tests/.pytest_cache/README.md
openet/core/tests/.pytest_cache/v/cache/lastfailed
openet/core/tests/.pytest_cache/v/cache/nodeids
openet/core/tests/.pytest_cache/v/cache/stepwise
openet_core.egg-info/PKG-INFO
openet_core.egg-info/SOURCES.txt
openet_core.egg-info/dependency_links.txt
openet_core.egg-info/requires.txt
openet_core.egg-info/top_level.txt