Metadata-Version: 2.4
Name: openet-core
Version: 0.8.1
Summary: OpenET Core Components
Author-email: Charles Morton <charles.morton@dri.edu>
License: Apache-2.0
Project-URL: Homepage, https://github.com/Open-ET/openet-core
Keywords: OpenET,Earth Engine,Evapotranspiration,Landsat
Classifier: Programming Language :: Python :: 3
Classifier: License :: OSI Approved :: Apache Software License
Classifier: Operating System :: OS Independent
Requires-Python: >=3.9
License-File: LICENSE
Requires-Dist: earthengine-api>=1.5.2
Requires-Dist: python-dateutil
Provides-Extra: test
Requires-Dist: pytest; extra == "test"
Dynamic: license-file
